setup.py
gaevalidator/__init__.py
gaevalidator/base.py
gaevalidator.egg-info/PKG-INFO
gaevalidator.egg-info/SOURCES.txt
gaevalidator.egg-info/dependency_links.txt
gaevalidator.egg-info/not-zip-safe
gaevalidator.egg-info/top_level.txt
gaevalidator/ndb/__init__.py
gaevalidator/ndb/validator.py